ipynb_strip_copy/__init__.py
ipynb_strip_copy/__main__.py
ipynb_strip_copy/command.py
ipynb_strip_copy/count_points.py
ipynb_strip_copy/file_ipynb.py
ipynb_strip_copy/search_apply.py
ipynb_strip_copy-0.1.5.dist-info/LICENSE
ipynb_strip_copy-0.1.5.dist-info/METADATA
ipynb_strip_copy-0.1.5.dist-info/WHEEL
ipynb_strip_copy-0.1.5.dist-info/top_level.txt
ipynb_strip_copy-0.1.5.dist-info/RECORD
