Metadata-Version: 2.1
Name: ipynb_strip_copy
Version: 0.1.5
Summary: makes student / TA copy of ipynb from rubric version
Author-email: Matt Higger <matt.higger@gmail.com>
License: MIT License
Project-URL: Homepage, https://github.com/matthigger/ipynb_strip_copy
Classifier: Programming Language :: Python :: 3
Classifier: Operating System :: OS Independent
Requires-Python: >=3.7
License-File: LICENSE
